odoo/addons/helpdesk_mgmt_timesheet/README.rst
odoo/addons/helpdesk_mgmt_timesheet/__init__.py
odoo/addons/helpdesk_mgmt_timesheet/__manifest__.py
odoo/addons/helpdesk_mgmt_timesheet/demo/helpdesk_mgmt_timesheet_demo.xml
odoo/addons/helpdesk_mgmt_timesheet/i18n/ca.po
odoo/addons/helpdesk_mgmt_timesheet/i18n/es.po
odoo/addons/helpdesk_mgmt_timesheet/i18n/fr.po
odoo/addons/helpdesk_mgmt_timesheet/i18n/fr_FR.po
odoo/addons/helpdesk_mgmt_timesheet/i18n/helpdesk_mgmt_timesheet.pot
odoo/addons/helpdesk_mgmt_timesheet/i18n/pt_BR.po
odoo/addons/helpdesk_mgmt_timesheet/i18n/sl.po
odoo/addons/helpdesk_mgmt_timesheet/models/__init__.py
odoo/addons/helpdesk_mgmt_timesheet/models/helpdesk_ticket.py
odoo/addons/helpdesk_mgmt_timesheet/models/helpdesk_ticket_team.py
odoo/addons/helpdesk_mgmt_timesheet/models/hr_timesheet.py
odoo/addons/helpdesk_mgmt_timesheet/readme/CONFIGURE.rst
odoo/addons/helpdesk_mgmt_timesheet/readme/CONTRIBUTORS.rst
odoo/addons/helpdesk_mgmt_timesheet/readme/DESCRIPTION.rst
odoo/addons/helpdesk_mgmt_timesheet/readme/USAGE.rst
odoo/addons/helpdesk_mgmt_timesheet/report/report_timesheet_templates.xml
odoo/addons/helpdesk_mgmt_timesheet/static/description/icon.png
odoo/addons/helpdesk_mgmt_timesheet/static/description/index.html
odoo/addons/helpdesk_mgmt_timesheet/tests/__init__.py
odoo/addons/helpdesk_mgmt_timesheet/tests/test_helpdesk_mgmt_timesheet.py
odoo/addons/helpdesk_mgmt_timesheet/views/helpdesk_team_view.xml
odoo/addons/helpdesk_mgmt_timesheet/views/helpdesk_ticket_view.xml
odoo/addons/helpdesk_mgmt_timesheet/views/hr_timesheet_view.xml
odoo12_addon_helpdesk_mgmt_timesheet-12.0.1.2.1.dist-info/METADATA
odoo12_addon_helpdesk_mgmt_timesheet-12.0.1.2.1.dist-info/WHEEL
odoo12_addon_helpdesk_mgmt_timesheet-12.0.1.2.1.dist-info/top_level.txt
odoo12_addon_helpdesk_mgmt_timesheet-12.0.1.2.1.dist-info/RECORD
