Metadata-Version: 2.1
Name: odoo12-addon-helpdesk-mgmt-timesheet
Version: 12.0.1.2.1
Summary: Add HR Timesheet to the tickets for Helpdesk Management.
Home-page: https://github.com/OCA/helpdesk
Author: Aresoltec Canarias, Punt Sistemes, SDi Soluciones Digitales, Solvos, Odoo Community Association (OCA)
Author-email: support@odoo-community.org
License: AGPL-3
Platform: UNKNOWN
Classifier: Programming Language :: Python
Classifier: Framework :: Odoo
Classifier: License :: OSI Approved :: GNU Affero General Public License v3
Requires-Python: >=3.5
Requires-Dist: odoo12-addon-helpdesk-mgmt-project
Requires-Dist: odoo (<12.1dev,>=12.0a)
